chikbip158.cpython-313-x86_64-linux-gnu.so
chikbip158-1.5.3.dist-info/METADATA
chikbip158-1.5.3.dist-info/RECORD
chikbip158-1.5.3.dist-info/top_level.txt
chikbip158-1.5.3.dist-info/WHEEL
chikbip158-1.5.3.dist-info/licenses/LICENSE
