Metadata-Version: 2.4
Name: chikbip158
Version: 1.5.3
Summary: Chik BIP158 (wraps C++)
Home-page: https://github.com/Chik-Network/chikbip158
Author: Mariano Sorgente
Author-email: admin@chiknetwork.com
License: Apache License
Requires-Python: >=3.7
License-File: LICENSE
Dynamic: author
Dynamic: author-email
Dynamic: description
Dynamic: description-content-type
Dynamic: home-page
Dynamic: license
Dynamic: license-file
Dynamic: requires-python
Dynamic: summary
